localcosmos_appkit_utils/AppImageCreator.py
localcosmos_appkit_utils/AppTheme.py
localcosmos_appkit_utils/MetaAppDefinition.py
localcosmos_appkit_utils/__init__.py
localcosmos_appkit_utils/image_utils.py
localcosmos_appkit_utils/logger.py
localcosmos_appkit_utils/resources/images/adaptive_launcher_background.png
localcosmos_appkit_utils/resources/images/adaptive_launcher_background.svg
localcosmos_appkit_utils-0.3.dist-info/LICENSE
localcosmos_appkit_utils-0.3.dist-info/METADATA
localcosmos_appkit_utils-0.3.dist-info/WHEEL
localcosmos_appkit_utils-0.3.dist-info/top_level.txt
localcosmos_appkit_utils-0.3.dist-info/RECORD
