Metadata-Version: 2.1
Name: localcosmos-appkit-utils
Version: 0.3
Summary: Local Cosmos AppKit utils. Creates images and more for mobile apps created with Local Cosmos.
Home-page: https://github.com/SiSol-Systems/localcosmos-appkit-utils
Author: Thomas Uher
Author-email: thomas.uher@sisol-systems.com
License: UNKNOWN
Project-URL: Bug Tracker, https://github.com/SiSol-Systems/localcosmos-appkit-utils/issues
Platform: UNKNOWN
Classifier: Programming Language :: Python :: 3
Classifier: License :: OSI Approved :: MIT License
Classifier: Operating System :: OS Independent
Requires-Python: >=3.6
Requires-Dist: Pillow
